ballfish/__init__.py
ballfish/distribution.py
ballfish/projective.py
ballfish/projective_transform.py
ballfish/py.typed
ballfish/transformation.py
ballfish/truncnorm.py
ballfish-0.4.1.dist-info/licenses/LICENSE
ballfish-0.4.1.dist-info/METADATA
ballfish-0.4.1.dist-info/WHEEL
ballfish-0.4.1.dist-info/top_level.txt
ballfish-0.4.1.dist-info/RECORD
