Metadata-Version: 2.4
Name: ballfish
Version: 0.4.1
Summary: Image augmentation library
Author-email: Arseniy Terekhin <senyai@gmail.com>
License: MIT
Project-URL: Homepage, https://github.com/iitpvisionlab/ballfish
Project-URL: Documentation, https://ballfish.readthedocs.io/
Project-URL: Bug Reports, https://github.com/iitpvisionlab/ballfish/issues
Project-URL: Source, https://github.com/iitpvisionlab/ballfish
Classifier: Programming Language :: Python :: 3
Classifier: License :: OSI Approved :: MIT License
Classifier: Operating System :: OS Independent
Classifier: Typing :: Typed
Requires-Python: >=3.10
License-File: LICENSE
Requires-Dist: torchvision
Requires-Dist: torch
Requires-Dist: scipy
Dynamic: license-file
